_matrix_hal.cpython-35m-arm-linux-gnueabihf.so
matrix_lite/__init__.py
matrix_lite/colour.py
matrix_lite/led.py
matrix_lite/sensors.py
matrix_lite-0.0.8.dist-info/LICENSE
matrix_lite-0.0.8.dist-info/METADATA
matrix_lite-0.0.8.dist-info/WHEEL
matrix_lite-0.0.8.dist-info/top_level.txt
matrix_lite-0.0.8.dist-info/RECORD
