Metadata-Version: 2.1
Name: matrix-lite
Version: 0.0.8
Summary: A wrapper for MATRIX HAL in Python
Home-page: https://github.com/matrix-io/matrix-lite-py
Author: MATRIX
Author-email: devel@matrixlabs.ai
License: UNKNOWN
Platform: UNKNOWN
Classifier: Programming Language :: Python :: 3.5
Classifier: Programming Language :: Python :: 3.7
